koa_like_flask_logger/__init__.py
koa_like_flask_logger-0.0.2.dist-info/METADATA
koa_like_flask_logger-0.0.2.dist-info/WHEEL
koa_like_flask_logger-0.0.2.dist-info/top_level.txt
koa_like_flask_logger-0.0.2.dist-info/RECORD
