Metadata-Version: 2.1
Name: koa-like-flask-logger
Version: 0.0.2
Summary: Add a koa-like logger for flask
Home-page: https://github.com/paradoxxxzero/koa_like_flask_logger
Author: Florian Mounier
Author-email: UNKNOWN
License: MIT
Platform: UNKNOWN
Requires-Dist: flask
